cuda/tile/VERSION
cuda/tile/__init__.py
cuda/tile/_by_target.py
cuda/tile/_cext.cpython-312-aarch64-linux-gnu.so
cuda/tile/_cext.pyi
cuda/tile/_compile.py
cuda/tile/_compiler_options.py
cuda/tile/_const_utils.py
cuda/tile/_context.py
cuda/tile/_coroutine_util.py
cuda/tile/_datatype.py
cuda/tile/_debug.py
cuda/tile/_exception.py
cuda/tile/_execution.py
cuda/tile/_ir2bytecode.py
cuda/tile/_load_libcuda.py
cuda/tile/_memory_model.py
cuda/tile/_mutex.py
cuda/tile/_numeric_semantics.py
cuda/tile/_stub.py
cuda/tile/_version.py
cuda/tile/_bytecode/__init__.py
cuda/tile/_bytecode/attribute.py
cuda/tile/_bytecode/basic.py
cuda/tile/_bytecode/code_builder.py
cuda/tile/_bytecode/constant.py
cuda/tile/_bytecode/debug_info.py
cuda/tile/_bytecode/encodings.py
cuda/tile/_bytecode/float.py
cuda/tile/_bytecode/type.py
cuda/tile/_bytecode/writer.py
cuda/tile/_ir/__init__.py
cuda/tile/_ir/hir.py
cuda/tile/_ir/ir.py
cuda/tile/_ir/load_store_impl.py
cuda/tile/_ir/op_impl.py
cuda/tile/_ir/ops.py
cuda/tile/_ir/ops_utils.py
cuda/tile/_ir/scope.py
cuda/tile/_ir/type.py
cuda/tile/_ir/typing_support.py
cuda/tile/_passes/__init__.py
cuda/tile/_passes/alias_analysis.py
cuda/tile/_passes/ast2hir.py
cuda/tile/_passes/code_motion.py
cuda/tile/_passes/dce.py
cuda/tile/_passes/eliminate_assign_ops.py
cuda/tile/_passes/hir2ir.py
cuda/tile/_passes/loop_split.py
cuda/tile/_passes/rewrite_patterns.py
cuda/tile/_passes/token_order.py
cuda_tile-1.1.0.dist-info/licenses/LICENSES/Apache-2.0.txt
cuda_tile-1.1.0.dist-info/METADATA
cuda_tile-1.1.0.dist-info/WHEEL
cuda_tile-1.1.0.dist-info/top_level.txt
cuda_tile-1.1.0.dist-info/RECORD
