Metadata-Version: 2.4
Name: cuda-tile
Version: 1.1.0
Summary: CUDA Tile Compiler
Author: NVIDIA Corporation
License-Expression: Apache-2.0
Project-URL: Homepage, https://github.com/nvidia/cutile-python
Project-URL: Repository, https://github.com/nvidia/cutile-python
Project-URL: documentation, https://docs.nvidia.com/cuda/cutile-python
Project-URL: Bug Tracker, https://github.com/nvidia/cutile-python/issues
Classifier: Development Status :: 5 - Production/Stable
Classifier: Environment :: GPU :: NVIDIA CUDA :: 13
Classifier: Intended Audience :: Developers
Classifier: Programming Language :: Python :: 3.10
Classifier: Programming Language :: Python :: 3.11
Classifier: Programming Language :: Python :: 3.12
Classifier: Programming Language :: Python :: 3.13
Classifier: Programming Language :: Python :: Implementation :: CPython
Classifier: Topic :: Software Development :: Compilers
Requires-Python: <3.14,>=3.10
License-File: LICENSES/Apache-2.0.txt
Requires-Dist: typing-extensions
Dynamic: license-file
